meconf/__init__.py
meconf/config.py
meconf/exceptions.py
meconf-0.0.2.dist-info/DESCRIPTION.rst
meconf-0.0.2.dist-info/METADATA
meconf-0.0.2.dist-info/RECORD
meconf-0.0.2.dist-info/WHEEL
meconf-0.0.2.dist-info/metadata.json
meconf-0.0.2.dist-info/top_level.txt
meconf-0.0.2.dist-info/zip-safe
