Metadata-Version: 2.0
Name: meconf
Version: 0.0.2
Summary: UNKNOWN
Home-page: https://github.com/RockingRolli/meconf
Author: Roland von Ohlen
Author-email: webwork@rvo-host.net
License: UNKNOWN
Keywords: config
Platform: UNKNOWN
Classifier: Development Status :: 3 - Alpha
Classifier: Programming Language :: Python
Provides-Extra: develop
Requires-Dist: pytest (==3.4.1); extra == 'develop'
Requires-Dist: pytest-cov (==2.5.1); extra == 'develop'
Requires-Dist: pytest-env (==0.6.2); extra == 'develop'
Requires-Dist: pylint (==1.8.2); extra == 'develop'
Requires-Dist: twine (==1.9.1); extra == 'develop'
